LICENSE
README.md
setup.py
django_admin_chart/__init__.py
django_admin_chart/chart.py
django_admin_chart/chart_base.py
django_admin_chart/chart_color.py
django_admin_chart/chart_render.py
django_admin_chart/statistics.py
django_admin_chart.egg-info/PKG-INFO
django_admin_chart.egg-info/SOURCES.txt
django_admin_chart.egg-info/dependency_links.txt
django_admin_chart.egg-info/requires.txt
django_admin_chart.egg-info/top_level.txt
django_admin_chart/templates/django_admin_chart/duel_bar_chart.html
django_admin_chart/templates/django_admin_chart/one_bar_chart.html
django_admin_chart/templates/django_admin_chart/one_bar_one_pie_chart.html
django_admin_chart/templates/django_admin_chart/components/chart_statistics.html
django_admin_chart/templates/django_admin_chart/widgets/button.html
django_admin_chart/templates/django_admin_chart/widgets/chart_bar.html
django_admin_chart/templates/django_admin_chart/widgets/chart_pie.html
django_admin_chart/templates/django_admin_chart/widgets/select.html